sonar/__init__.py
sonar/py.typed
sonar/cards/blaser_2_0.yaml
sonar/cards/laser2_text_encoder.yaml
sonar/cards/sonar_mutox.yaml
sonar/cards/sonar_speech_encoder.yaml
sonar/cards/text_sonar_basic_decoder.yaml
sonar/cards/text_sonar_basic_encoder.yaml
sonar/cards/text_sonar_finetuned_decoder.yaml
sonar/inference_pipelines/__init__.py
sonar/inference_pipelines/mutox_speech.py
sonar/inference_pipelines/speech.py
sonar/inference_pipelines/text.py
sonar/inference_pipelines/utils.py
sonar/models/__init__.py
sonar/models/encoder_model.py
sonar/models/blaser/__init__.py
sonar/models/blaser/checkpoint.py
sonar/models/blaser/config.py
sonar/models/blaser/factory.py
sonar/models/blaser/loader.py
sonar/models/blaser/model.py
sonar/models/laser2_text/__init__.py
sonar/models/laser2_text/checkpoint.py
sonar/models/laser2_text/config.py
sonar/models/laser2_text/factory.py
sonar/models/laser2_text/tokenizer.py
sonar/models/mutox/__init__.py
sonar/models/mutox/checkpoint.py
sonar/models/mutox/config.py
sonar/models/mutox/factory.py
sonar/models/mutox/loader.py
sonar/models/mutox/model.py
sonar/models/sonar_speech/__init__.py
sonar/models/sonar_speech/checkpoint.py
sonar/models/sonar_speech/config.py
sonar/models/sonar_speech/factory.py
sonar/models/sonar_speech/model.py
sonar/models/sonar_text/__init__.py
sonar/models/sonar_text/checkpoint.py
sonar/models/sonar_text/config.py
sonar/models/sonar_text/factory.py
sonar/models/sonar_text/model.py
sonar/models/sonar_translation/__init__.py
sonar/models/sonar_translation/factory.py
sonar/models/sonar_translation/model.py
sonar/nn/__init__.py
sonar/nn/conditional_decoder_model.py
sonar/nn/encoder_pooler.py
sonar/nn/laser_lstm_encoder.py
sonar/nn/sequence.py
sonar_space-0.5.0.dist-info/entry_points.txt
sonar_space-0.5.0.dist-info/licenses/LICENSE.md
sonar_space-0.5.0.dist-info/WHEEL
sonar_space-0.5.0.dist-info/METADATA
sonar_space-0.5.0.dist-info/RECORD
