Metadata-Version: 2.4
Name: sonar-space
Version: 0.5.0
Summary: SONAR provides a set of speech and text encoders for multilingual, multimodal semantic embedding.
Keywords: sentence embeddings,sentence representation,sentence encoder,sonar models,speech2speech,text2text,speech2text,text2speech,multi-modal models,multi-language models
Author: Meta AI Research
Requires-Python: >=3.10
Classifier: Topic :: Scientific/Engineering
Classifier: Development Status :: 4 - Beta
License-File: LICENSE.md
Requires-Dist: fairseq2>=0.5.2
Requires-Dist: numpy>=1.21
Requires-Dist: torch
Requires-Dist: torchaudio
Requires-Dist: sox
Requires-Dist: soundfile
Requires-Dist: tqdm
Requires-Dist: typing_extensions
Requires-Dist: torch==2.6.0+cpu ; extra == "cpu"
Requires-Dist: torchaudio==2.6.0+cpu ; extra == "cpu"
Requires-Dist: fairseq2n>=0.5.2 ; extra == "cpu"
Requires-Dist: fairseq2>=0.5.2 ; extra == "cpu"
Requires-Dist: pytest>=4.3.0 ; extra == "dev"
Requires-Dist: pytest-asyncio>=0.15.0 ; extra == "dev"
Requires-Dist: pytest-cov>=2.6.1 ; extra == "dev"
Requires-Dist: coverage[toml]>=5.1 ; extra == "dev"
Requires-Dist: black==25.1.0 ; extra == "dev"
Requires-Dist: isort>=5.10.1 ; extra == "dev"
Requires-Dist: mypy>=0.782 ; extra == "dev"
Requires-Dist: pylint>=2.8.0 ; extra == "dev"
Requires-Dist: flake8 ; extra == "dev"
Requires-Dist: types-tqdm ; extra == "dev"
Requires-Dist: transformers>=4.44.0 ; extra == "hg"
Requires-Dist: datasets>=2.20.0 ; extra == "hg"
Requires-Dist: evaluate>=0.4.2 ; extra == "hg"
Requires-Dist: rouge_score>=0.1.2 ; extra == "hg"
Requires-Dist: nltk>=3.9 ; extra == "hg"
Requires-Dist: absl-py>=2.1.0 ; extra == "hg"
Project-URL: Source, https://github.com/facebookresearch/SONAR
Project-URL: Tracker, https://github.com/facebookresearch/SONAR/issues
Provides-Extra: cpu
Provides-Extra: dev
Provides-Extra: hg
